[
  {
    "title": "Ө.Шижир: Цахилгаан, дулааны үнэ нэмэхэд \"А\" гэж дуугараагүй гишүүд тамхины татвар нэмэхийг эсэргүүцэж байна",
    "publish_date": "Thu, 25 Jun 2026 18:54:00 +0800",
    "source": "IKON",
    "url": "https://ikon.mn/n/3ojb"
  },
  {
    "title": "Дубайн нэгэн үнэт эдлэлийн дэлгүүрийн эзэн алмаазан шигтгээтэй ДАШТ-ий цомыг легогоор бүтээжээ",
    "publish_date": "Thu, 25 Jun 2026 17:31:00 +0800",
    "source": "IKON",
    "url": "https://ikon.mn/n/3oj9"
  },
  {
    "title": "М.Нарантуяа-Нара: Эмэгтэйчүүд эрүүл мэндээ бодоод электрон тамхи татъя гэтэл таслан зогсоочхож байгаа юм биш байгаа",
    "publish_date": "Thu, 25 Jun 2026 17:13:00 +0800",
    "source": "IKON",
    "url": "https://ikon.mn/n/3oj8"
  },
  {
    "title": "Нийслэлийн авто замын түгжрэлийг бууруулах төслийг БНСУ-ын талын 2.7 тэрбум воны буцалтгүй тусламжаар хэрэгжүүлнэ",
    "publish_date": "Thu, 25 Jun 2026 16:53:00 +0800",
    "source": "IKON",
    "url": "https://ikon.mn/n/3oj6"
  },
  {
    "title": "Төв цэнгэлдэх хүрээлэн 2026 онд зохион байгуулах арга хэмжээний сонгон шалгаруулалт зарлалаа",
    "publish_date": "Thu, 25 Jun 2026 16:35:00 +0800",
    "source": "IKON",
    "url": "https://ikon.mn/n/3ohr"
  },
  {
    "title": "Капитрон банк: ТЕНДЕРИЙН УРИЛГА",
    "publish_date": "Thu, 25 Jun 2026 16:31:00 +0800",
    "source": "IKON",
    "url": "https://ikon.mn/n/3oj5"
  },
  {
    "title": "Моносын “Уламжлалт болон ургамлын гаралтай эмийн үйлдвэр” нээлтээ хийлээ",
    "publish_date": "Thu, 25 Jun 2026 15:41:00 +0800",
    "source": "IKON",
    "url": "https://ikon.mn/n/3oj3"
  },
  {
    "title": "О.Номинчимэг гишүүний өргөн барьсан электрон тамхинаас татвар авах агуулгатай хуулийн төслийг хэлэлцэж байна",
    "publish_date": "Thu, 25 Jun 2026 15:33:00 +0800",
    "source": "IKON",
    "url": "https://ikon.mn/n/3oiy"
  },
  {
    "title": "З.Мэндсайхан: Хамрын тамхинаас авдаг байсан 20 хувийн гаалийн татварыг онцгой албан татвараар тооцно",
    "publish_date": "Thu, 25 Jun 2026 15:25:00 +0800",
    "source": "IKON",
    "url": "https://ikon.mn/n/3oj2"
  },
  {
    "title": "Голомт банкны SocialPay аппликэйшнээр Төрийн банкны “И-Билл үйлчилгээ”-г ашиглах боломжтой боллоо",
    "publish_date": "Thu, 25 Jun 2026 15:13:00 +0800",
    "source": "IKON",
    "url": "https://ikon.mn/n/3oj1"
  },
  {
    "title": "Боксчин Т.Энхтөр допингийн зөрчил гаргаснаар эрхээ хоёр жилээр хасууллаа",
    "publish_date": "Thu, 25 Jun 2026 15:05:00 +0800",
    "source": "IKON",
    "url": "https://ikon.mn/n/3oj0"
  },
  {
    "title": "Э.Тамир: Бүх хүний тэтгэвэрт гарах насыг нэмэгдүүлсэн хуулийн төслийг хэлэлцэх гэж байна",
    "publish_date": "Thu, 25 Jun 2026 15:02:00 +0800",
    "source": "IKON",
    "url": "https://ikon.mn/n/3oiw"
  },
  {
    "title": "Төмөр замын дагуух хориг хашааг зэрлэг амьтдад ээлтэй байдлаар шинэчилнэ",
    "publish_date": "Thu, 25 Jun 2026 14:58:00 +0800",
    "source": "IKON",
    "url": "https://ikon.mn/n/3oiz"
  },
  {
    "title": "СОНС: Playtime 2026-д оролцох амьд хөгжмийн БҮХ ХАМТЛАГ, УРАН БҮТЭЭЛЧИД",
    "publish_date": "Thu, 25 Jun 2026 14:43:00 +0800",
    "source": "IKON",
    "url": "https://ikon.mn/lr/3ofl"
  },
  {
    "title": "АН-ын бүлэг Орон сууцны санхүүжилтийн төрөлжсөн банкны тухай хуулийн төсөл дээр ажлын гурав хоногийн завсарлага авлаа",
    "publish_date": "Thu, 25 Jun 2026 14:38:00 +0800",
    "source": "IKON",
    "url": "https://ikon.mn/n/3oid"
  },
  {
    "title": "\"Францын талтай хамтран Улаанбаатар дахь нислэгийн хөдөлгөөний удирдлагын төвийн тоног төхөөрөмжийг шинэчилж, Сайншандад нөөц төв байгуулна\"",
    "publish_date": "Thu, 25 Jun 2026 14:26:00 +0800",
    "source": "IKON",
    "url": "https://ikon.mn/n/3oiu"
  },
  {
    "title": "Ш.Энхийн-Од сонгогдсонгүй. Гэхдээ...",
    "publish_date": "Thu, 25 Jun 2026 13:36:00 +0800",
    "source": "IKON",
    "url": "https://ikon.mn/n/3oiv"
  },
  {
    "title": "Ж.Мөнгөншагай: Хүнд, хортой нөхцөлд ажилладаг хүмүүсийг тэтгэвэрт гаргалгүй ажлын байран дээр нь алах зорилготой хуулийг эсэргүүцэж байна",
    "publish_date": "Thu, 25 Jun 2026 13:26:00 +0800",
    "source": "IKON",
    "url": "https://ikon.mn/n/3oiq"
  },
  {
    "title": "С.Цэнгүүн: Төрийн өмчит компаниудын удирдлагуудын цалин маш өндөр байна",
    "publish_date": "Thu, 25 Jun 2026 13:00:00 +0800",
    "source": "IKON",
    "url": "https://ikon.mn/n/3oit"
  },
  {
    "title": "Өөрийн бэлдсэн хэмжээндээ ЭШ-аа өгөх орчныг бүрдүүлж байгаа учир ойр орчимд нь өндөр хаазлах, сигнал дуугаргахгүй байхыг зөвлөв",
    "publish_date": "Thu, 25 Jun 2026 12:58:00 +0800",
    "source": "IKON",
    "url": "https://ikon.mn/n/3oip"
  },
  {
    "title": "\"Хүүхдийн ордон 2\" нь шинжлэх ухаан, технологи, инновацын төв болно",
    "publish_date": "Thu, 25 Jun 2026 12:57:00 +0800",
    "source": "IKON",
    "url": "https://ikon.mn/n/3oir"
  },
  {
    "title": "ХХБ БНФУ-ын Bpifrance банктай 19.55 сая еврогийн санхүүжилтийн гэрээ байгууллаа",
    "publish_date": "Thu, 25 Jun 2026 12:56:00 +0800",
    "source": "IKON",
    "url": "https://ikon.mn/n/3ois"
  },
  {
    "title": "ФОТО: Элсэлтийн шалгалтын анхны оноо буюу 100 онооноос хэдэн оноо авсныг харуулж буй явц",
    "publish_date": "Thu, 25 Jun 2026 12:21:00 +0800",
    "source": "IKON",
    "url": "https://ikon.mn/n/3oin"
  },
  {
    "title": "БҮТ: Шалгалтын төв болгон дээр эмч, сэтгэлзүйчид ажиллаж байна",
    "publish_date": "Thu, 25 Jun 2026 11:56:00 +0800",
    "source": "IKON",
    "url": "https://ikon.mn/n/3oik"
  },
  {
    "title": "Н.Алтанхуяг: Зэсийн үнэ өсөж байгаа цаг үед АМНАТ-ийг гурав дахин бууруулна гэлээ. Г.Дамдинням хэний эрх ашигт үйлчилж байна вэ",
    "publish_date": "Thu, 25 Jun 2026 11:48:00 +0800",
    "source": "IKON",
    "url": "https://ikon.mn/n/3oim"
  },
  {
    "title": "“Петрочайна Дачин Тамсаг”, “Доншен газрын тос” компаниудад тавьсан татвар, нийгмийн даатгал, аудитын актын төлбөрийг \"хаах\" хуулийг хэлэлцэж байна",
    "publish_date": "Thu, 25 Jun 2026 11:44:00 +0800",
    "source": "IKON",
    "url": "https://ikon.mn/n/3oil"
  },
  {
    "title": "Мексик, Швейцар, Бразил хэсгээ тэргүүллээ",
    "publish_date": "Thu, 25 Jun 2026 11:35:00 +0800",
    "source": "IKON",
    "url": "https://ikon.mn/n/3oij"
  },
  {
    "title": "Олон улсын түншлэлээс дэлхийн үнэлгээ рүү: Интермед IUHW эмнэлэг олон улсын чанарын баталгаажуулалт авлаа",
    "publish_date": "Thu, 25 Jun 2026 11:09:00 +0800",
    "source": "IKON",
    "url": "https://ikon.mn/n/3oii"
  },
  {
    "title": "12 жил нөхрийнхөө хараа хяналт дор хоригдож байсан франц эмэгтэйг Пакистаны эрх баригчид чөлөөлжээ",
    "publish_date": "Thu, 25 Jun 2026 10:46:00 +0800",
    "source": "IKON",
    "url": "https://ikon.mn/n/3oia"
  },
  {
    "title": "\"Хүрээ цам-Даншиг наадам 2026\"-ын үеэр хоол үйлдвэрлэл, үйлчилгээний 170 гаруй цэг ажиллана",
    "publish_date": "Thu, 25 Jun 2026 10:45:00 +0800",
    "source": "IKON",
    "url": "https://ikon.mn/n/3oih"
  },
  {
    "title": "Эмнэлгийн тусламж, үйлчилгээний тухай, Төрийн нууцын тухай хуулийн төслүүдийг хэлэлцэхийг дэмжлээ",
    "publish_date": "Thu, 25 Jun 2026 00:00:00 GMT",
    "source": "蒙古国大呼拉尔",
    "url": "https://www.parliament.mn/nn/77691/"
  },
  {
    "title": "“Алтай дамнасан тогтвортой байдлын яриа хэлэлцээ-2026” олон улсын чуулганыг дөрөв дэх удаагаа зохион байгуулна",
    "publish_date": "Thu, 25 Jun 2026 00:00:00 GMT",
    "source": "蒙古国大呼拉尔",
    "url": "https://www.parliament.mn/nn/77693/"
  },
  {
    "title": "УИХ-ын дарга С.Бямбацогт Эрчим хүчний салбарын инженер, мэргэжилтнүүдтэй уулзлаа",
    "publish_date": "Thu, 25 Jun 2026 00:00:00 GMT",
    "source": "蒙古国大呼拉尔",
    "url": "https://www.parliament.mn/nn/77692/"
  },
  {
    "title": "БШУДХ: Шинжлэх ухаан, технологийн салбарт тулгамдсан асуудал, бодлогын шийдлийн талаарх мэдээллийг сонсож, Байнгын хорооны тогтоолын төслийг танилцууллаа",
    "publish_date": "Thu, 25 Jun 2026 00:00:00 GMT",
    "source": "蒙古国大呼拉尔",
    "url": "https://www.parliament.mn/nn/77690/"
  },
  {
    "title": "ЭЗБХ: Төрийн болон орон нутгийн өмчит компанийн бүтээмж, ил тод байдал, засаглалыг сайжруулах тухай хуулийн төслийн эцсийн хэлэлцүүлгийг хийв",
    "publish_date": "Thu, 25 Jun 2026 00:00:00 GMT",
    "source": "蒙古国大呼拉尔",
    "url": "https://www.parliament.mn/nn/77684/"
  },
  {
    "title": "ХЗБХ: Төсвийн төслийг улсын хөгжлийн жилийн төлөвлөгөөнд нийцүүлж, үнэн зөв, бодитой төлөвлөж, тайлагнаж хэвших шаардлагатайг анхааруулав",
    "publish_date": "Thu, 25 Jun 2026 00:00:00 GMT",
    "source": "蒙古国大呼拉尔",
    "url": "https://www.parliament.mn/nn/77683/"
  },
  {
    "title": "ТББХ: Нэр дэвшигч Ж.Сүхбаатар, Г.Эрдэнэбат нарыг Үндсэн хуулийн цэцийн гишүүнээр томилохыг дэмжлээ",
    "publish_date": "Thu, 25 Jun 2026 00:00:00 GMT",
    "source": "蒙古国大呼拉尔",
    "url": "https://www.parliament.mn/nn/77682/"
  },
  {
    "title": "ТБХ:Онцгой албан татварын тухай хуульд нэмэлт, өөрчлөлт оруулах тухай хуулийн төслийг хэлэлцэхийг дэмжиж, Улсын Их Хурлын тогтоолын төслийн хоёр дахь хэлэлцүүлгийг хийлээ",
    "publish_date": "Thu, 25 Jun 2026 00:00:00 GMT",
    "source": "蒙古国大呼拉尔",
    "url": "https://www.parliament.mn/nn/77681/"
  },
  {
    "title": "“Малчны тухай хуулийн хэрэгжилтийг дүгнэх, хууль тогтоомжийг хэрэгжүүлэх чиг үүрэг бүхий байгууллага, түүний удирдах албан тушаалтны үйл ажиллагаанд хяналт тавих, үнэлэх’’ сэдэвт сонсгол өндөрлөв",
    "publish_date": "Thu, 25 Jun 2026 00:00:00 GMT",
    "source": "蒙古国大呼拉尔",
    "url": "https://www.parliament.mn/nn/77677/"
  },
  {
    "title": "Улсын Их Хурлын гишүүн Л.Мөнхбаясгаланг Азийн парламентуудын усны асуудал хариуцсан Зөвлөлдөх зөвлөлд урилаа",
    "publish_date": "Thu, 25 Jun 2026 00:00:00 GMT",
    "source": "蒙古国大呼拉尔",
    "url": "https://www.parliament.mn/nn/77680/"
  },
  {
    "title": "УИХ-ын дарга С.Бямбацогт Австралийн Холбооны Улсаас Монгол Улсад суугаа Элчин сайд Лео Зенгийг хүлээн авч уулзав",
    "publish_date": "Thu, 25 Jun 2026 00:00:00 GMT",
    "source": "蒙古国大呼拉尔",
    "url": "https://www.parliament.mn/nn/77679/"
  },
  {
    "title": "БОХХААБХ: Монгол Улсын 2025 оны нэгдсэн төсвийн гүйцэтгэл, Засгийн газрын 2025 оны санхүүгийн нэгтгэсэн тайлангийн хоёр дахь хэлэлцүүлгийг хийлээ",
    "publish_date": "Thu, 25 Jun 2026 00:00:00 GMT",
    "source": "蒙古国大呼拉尔",
    "url": "https://www.parliament.mn/nn/77676/"
  },
  {
    "title": "МОНГОЛ УЛСЫН ЗАСГИЙН ГАЗРЫН 2026 ОНЫ 06 ДУГААР САРЫН 17-НЫ ӨДРИЙН 253 ДУГААР ТОГТООЛООР БАТЛАГДСАН “МЭРГЭЖЛИЙН НЭГДСЭН ХОЛБООГ БҮРТГЭХ ЖУРАМ”-ЫН ТАНИЛЦУУЛГЫГ ЕРӨНХИЙ САЙДЫН АЖЛЫН АЛБАНААС ХИЙХ ТУЛ МЭРГЭЖЛИЙН ХОЛБООДЫН ТӨЛӨӨЛЛИЙГ УРЬЖ БАЙНА",
    "publish_date": "Thu, 25 Jun 2026 10:15:16 +0000",
    "source": "蒙古国工业和矿产资源部",
    "url": "https://mmhi.gov.mn/2026/06/25/%d0%bc%d0%be%d0%bd%d0%b3%d0%be%d0%bb-%d1%83%d0%bb%d1%81%d1%8b%d0%bd-%d0%b7%d0%b0%d1%81%d0%b3%d0%b8%d0%b9%d0%bd-%d0%b3%d0%b0%d0%b7%d1%80%d1%8b%d0%bd-2026-%d0%be%d0%bd%d1%8b-06-%d0%b4%d1%83%d0%b3%d0%b0/"
  },
  {
    "title": "Хүмүүнлэгийн андууддаа талархал илэрхийллээ",
    "publish_date": "Thu, 25 Jun 2026 00:00:00 GMT",
    "source": "蒙古国紧急情况总局",
    "url": "https://nema.gov.mn/post/174979"
  },
  {
    "title": "Цагааннуур сум дахь эрэн хайх, аврах салбарын үйл ажиллагааг эхлүүллээ",
    "publish_date": "Thu, 25 Jun 2026 00:00:00 GMT",
    "source": "蒙古国紧急情况总局",
    "url": "https://nema.gov.mn/post/170820"
  },
  {
    "title": "Монгол Улсад төрийн цэргийн болон хууль сахиулах байгууллагын эмэгтэй алба хаагчид хурандаа цол олгож эхэлсний 30 жилийн ой өнөөдөр тохиож байна",
    "publish_date": "Thu, 25 Jun 2026 00:00:00 GMT",
    "source": "蒙古国紧急情况总局",
    "url": "https://nema.gov.mn/post/162024"
  },
  {
    "title": "\"ТӨРИЙН БОДЛОГО-ЖИЖИГ, ДУНД ҮЙЛДВЭР, ХАРЬЦУУЛСАН СУДАЛГАА\" НОМ УНШИГЧИЙН ГАР ДЭЭР ОЧЛОО",
    "publish_date": "Thu, 25 Jun 2026 00:00:00 GMT",
    "source": "中小企业局",
    "url": "https://sme.gov.mn/news/16203978159443/16203978159460/17766807135802",
    "category": "党政机关"
  },
  {
    "title": "Неймар 980 хоногийн дараа Бразилын шигшээ багийн төлөө тоглолоо",
    "publish_date": "Thu, 25 Jun 2026 00:00:00 GMT",
    "source": "蒙通社",
    "url": "https://montsame.mn/mn/read/403027",
    "category": "新闻媒体"
  },
  {
    "title": "COP17 бага хурлын хүрээнд “Сайн санаачилга, шилдэг шийдэл”-ийг хүлээн авч эхэллээ",
    "publish_date": "Thu, 25 Jun 2026 00:00:00 GMT",
    "source": "蒙通社",
    "url": "https://montsame.mn/mn/read/403123",
    "category": "新闻媒体"
  },
  {
    "title": "Ихэнх нутгаар өнөөдөр бороотой",
    "publish_date": "Thu, 25 Jun 2026 00:00:00 GMT",
    "source": "蒙通社",
    "url": "https://montsame.mn/mn/read/403026",
    "category": "新闻媒体"
  },
  {
    "title": "САЙД Ж.АЛДАРЖАВХЛАН ОЛОН УЛСЫН ОЮУТНЫ СПОРТЫН ХОЛБООНЫ ТӨЛӨӨЛӨГЧДИЙГ ХҮЛЭЭН АВЧ УУЛЗЛАА",
    "publish_date": "Thu, 25 Jun 2026 00:00:00 GMT",
    "source": "蒙古国文化体育旅游与青年部",
    "url": "https://mocsty.gov.mn/news/062503",
    "category": "党政机关"
  },
  {
    "title": "МОНГОЛ УЛСЫН ХҮҮХЭЛДЭЙН ТЕАТР “СИБИРЬ TERRA MAGICA” НААДАМД АМЖИЛТТАЙ ОРОЛЦЛОО",
    "publish_date": "Thu, 25 Jun 2026 00:00:00 GMT",
    "source": "蒙古国文化体育旅游与青年部",
    "url": "https://mocsty.gov.mn/news/062501",
    "category": "党政机关"
  },
  {
    "title": "“Автотээврийн хэрэгслийн бүртгэл хөтлөх, улсын дугаар олгох журам”-төслийн хэлэлцүүлэгт таныг урьж байна.",
    "publish_date": "Thu, 25 Jun 2026 00:00:00 GMT",
    "source": "道路与交通运输部",
    "url": "https://mrt.gov.mn/i/5112",
    "category": "党政机关"
  },
  {
    "title": "Нислэгийн хөдөлгөөний удирдлагын төвийн систем, тоног төхөөрөмжийн шинэчлэлийг санхүүжүүлэх экспортын зээлийн гэрээнүүдэд гарын үсэг зурлаа",
    "publish_date": "Thu, 25 Jun 2026 00:00:00 GMT",
    "source": "道路与交通运输部",
    "url": "https://mrt.gov.mn/i/5109",
    "category": "党政机关"
  },
  {
    "title": "Хөдлөх бүрэлдэхүүн жолоодох эрхийн үнэмлэх горилогчдын анхааралд",
    "publish_date": "Thu, 25 Jun 2026 00:00:00 GMT",
    "source": "道路与交通运输部",
    "url": "https://mrt.gov.mn/i/5108",
    "category": "党政机关"
  },
  {
    "title": "NEMA Podcast-17",
    "publish_date": "Thu, 25 Jun 2026 00:00:00 GMT",
    "source": "蒙古国紧急情况总局",
    "url": "https://nema.gov.mn/post/176687",
    "category": "党政机关"
  },
  {
    "title": "Венесуэлд 7.5 магнитудын хүчтэй газар хөдөлжээ",
    "publish_date": "Thu, 25 Jun 2026 00:00:00 GMT",
    "source": "蒙古国紧急情况总局",
    "url": "https://nema.gov.mn/post/176683",
    "category": "党政机关"
  },
  {
    "title": "Эмч,эмнэлгийн мэргэжилтнүүд мэдлэг, ур чадвараа  дээшлүүлж, харилцан туршлага солилцлоо",
    "publish_date": "Thu, 25 Jun 2026 00:00:00 GMT",
    "source": "蒙古国紧急情况总局",
    "url": "https://nema.gov.mn/post/176665",
    "category": "党政机关"
  },
  {
    "title": "ЭРЧИМ ХҮЧНИЙ САЛБАРЫН МЭДЭЭЛЭЛ ИРГЭН БҮРТ НЭЭЛТТЭЙ БОЛЛОО",
    "publish_date": "Thu, 25 Jun 2026 00:00:00 GMT",
    "source": "能源部",
    "url": "https://energy.gov.mn/post/176662",
    "category": "党政机关"
  },
  {
    "title": "СЭРГЭЭГДЭХ ЭРЧИМ ХҮЧНИЙ НӨӨЦ, ЭХ ҮҮСВЭРИЙН СУДАЛГАА ШИНЖИЛГЭЭ БОЛОН УС ЦАГ УУРЫН АЖИГЛАЛТЫН ЗОРИУЛАЛТТАЙ 15 НЭР ТӨРЛИЙН ТОНОГ ТӨХӨӨРӨМЖИЙГ ГААЛЬ, НӨАТ-ААС ЧӨЛӨӨЛӨХ ТОГТООЛЫГ БАТАЛЛАА",
    "publish_date": "Thu, 25 Jun 2026 00:00:00 GMT",
    "source": "气象与环境研究局",
    "url": "https://namem.gov.mn/d/news/846",
    "category": "党政机关"
  },
  {
    "title": "“Авлигатай тэмцэх Үндэсний хөтөлбөр”-ийн сургалт болов",
    "publish_date": "Thu, 25 Jun 2026 00:00:00 GMT",
    "source": "央行",
    "url": "https://www.mongolbank.mn/mn/r/12529",
    "category": "党政机关"
  },
  {
    "title": "\"Зууны мэдээ\" 2026.6.26: Онцлох контент...",
    "publish_date": "Thu, 25 Jun 2026 00:00:00 GMT",
    "source": "世纪新闻报",
    "url": "https://www.zms.mn/a/104516",
    "category": "新闻媒体"
  },
  {
    "title": "М.Энх-Од: Малын ээмгийг дахин боловсруулах боломжийг бүрдүүлсэн",
    "publish_date": "Thu, 25 Jun 2026 00:00:00 GMT",
    "source": "世纪新闻报",
    "url": "https://www.zms.mn/a/104515",
    "category": "新闻媒体"
  },
  {
    "title": "Г.Жамъянпүрэв: Польшийн багтай 0.1 онооны зөрүүтэй өрсөлдөж, эцсийн мөчид бид алтан медаль хүртлээ",
    "publish_date": "Thu, 25 Jun 2026 00:00:00 GMT",
    "source": "世纪新闻报",
    "url": "https://www.zms.mn/a/104514",
    "category": "新闻媒体"
  },
  {
    "title": "Б.Мэнд-Амар: АНУ-ын үндэсний сансрын төвд инженерээр ажиллахыг хүсдэг ч сур харваагаа орхихгүй",
    "publish_date": "Thu, 25 Jun 2026 00:00:00 GMT",
    "source": "世纪新闻报",
    "url": "https://www.zms.mn/a/104513",
    "category": "新闻媒体"
  },
  {
    "title": "А.Түвшинбаяр: Бүжиг бол сэтгэл мэдрэмж уран сэтгэмжийн нэгдэл",
    "publish_date": "Thu, 25 Jun 2026 00:00:00 GMT",
    "source": "世纪新闻报",
    "url": "https://www.zms.mn/a/104512",
    "category": "新闻媒体"
  },
  {
    "title": "Хатааж хаяхаас хатаамал хийж боловсруулах нь цэцгийн хаягдлыг бууруулна",
    "publish_date": "Thu, 25 Jun 2026 00:00:00 GMT",
    "source": "世纪新闻报",
    "url": "https://www.zms.mn/a/104511",
    "category": "新闻媒体"
  },
  {
    "title": "У.Анударь: Айдсаа хобби болгосон",
    "publish_date": "Thu, 25 Jun 2026 00:00:00 GMT",
    "source": "世纪新闻报",
    "url": "https://www.zms.mn/a/104510",
    "category": "新闻媒体"
  },
  {
    "title": "“Сайншандад бүсийн нислэгийн хөдөлгөөний удирдлагын нөөц төв байгуулна”",
    "publish_date": "Thu, 25 Jun 2026 00:00:00 GMT",
    "source": "世纪新闻报",
    "url": "https://www.zms.mn/a/104509",
    "category": "新闻媒体"
  },
  {
    "title": "Медаль хүртсэн тулаанчид олон улсын тэмцээнд оролцоно",
    "publish_date": "Thu, 25 Jun 2026 00:00:00 GMT",
    "source": "今日报",
    "url": "https://www.unuudur.mn/a/282638",
    "category": "新闻媒体"
  },
  {
    "title": "“Ялалтын маршал”-ын өндөр өртөг",
    "publish_date": "Thu, 25 Jun 2026 00:00:00 GMT",
    "source": "今日报",
    "url": "https://www.unuudur.mn/a/282635",
    "category": "新闻媒体"
  },
  {
    "title": "Б.БАЯРСАЙХАН: ЕХ, АНУ-ын олон хоригт орсон нь Монгол, Беларусийн эдийн засгийн хамтын ажиллагаанд томоохон сорилт болж байна",
    "publish_date": "Thu, 25 Jun 2026 00:00:00 GMT",
    "source": "今日报",
    "url": "https://www.unuudur.mn/a/282636",
    "category": "新闻媒体"
  },
  {
    "title": "Дээд шүүх улс төрийн найман намыг бүртгэлээс хасжээ",
    "publish_date": "Thu, 25 Jun 2026 00:00:00 GMT",
    "source": "今日报",
    "url": "https://www.unuudur.mn/a/282634",
    "category": "新闻媒体"
  },
  {
    "title": "ОХУ гаднаас шатахуун импортлох талаар судалж байна",
    "publish_date": "Thu, 25 Jun 2026 00:00:00 GMT",
    "source": "今日报",
    "url": "https://www.unuudur.mn/a/282633",
    "category": "新闻媒体"
  },
  {
    "title": "Сэрүүцэхээр ус руу орсон 40 хүн живж, амиа алдав",
    "publish_date": "Thu, 25 Jun 2026 00:00:00 GMT",
    "source": "今日报",
    "url": "https://www.unuudur.mn/a/282632",
    "category": "新闻媒体"
  },
  {
    "title": "Баруун  Европт улаан түвшний түгшүүр зарлаад байсан хэт  халууны урсгал аажмаар дорно зүг рүү шилжиж байна",
    "publish_date": "Thu, 25 Jun 2026 00:00:00 GMT",
    "source": "今日报",
    "url": "https://www.unuudur.mn/a/282649",
    "category": "新闻媒体"
  },
  {
    "title": "Завхан аймгийн Яруу суманд 3.8 магнитудын хүчтэй газар хөдлөлт боллоо",
    "publish_date": "Thu, 25 Jun 2026 00:00:00 GMT",
    "source": "今日报",
    "url": "https://www.unuudur.mn/a/282648",
    "category": "新闻媒体"
  },
  {
    "title": "Хөшөө Цайдамын музейн хаягийг бичихдээ түүхийн ноцтой алдаа гаргав",
    "publish_date": "Thu, 25 Jun 2026 00:00:00 GMT",
    "source": "今日报",
    "url": "https://www.unuudur.mn/a/282630",
    "category": "新闻媒体"
  },
  {
    "title": "Венесуэлийн газар хөдлөлтийн улмаас амиа алдсан хүний тоо 100,000 хүрэх  магадлалтай",
    "publish_date": "Thu, 25 Jun 2026 00:00:00 GMT",
    "source": "今日报",
    "url": "https://www.unuudur.mn/a/282644",
    "category": "新闻媒体"
  },
  {
    "title": "БНСУ-аас 468.3 сая ам.долларын бараа худалдан авчээ",
    "publish_date": "Thu, 25 Jun 2026 00:00:00 GMT",
    "source": "今日报",
    "url": "https://www.unuudur.mn/a/282629",
    "category": "新闻媒体"
  },
  {
    "title": "Даншиг наадмын өдрүүдэд 07:00-23:00 цагт хоёр чиглэлд 16 автобус иргэдэд үнэ төлбөргүй үйлчилнэ",
    "publish_date": "Thu, 25 Jun 2026 00:00:00 GMT",
    "source": "今日报",
    "url": "https://www.unuudur.mn/a/282642",
    "category": "新闻媒体"
  },
  {
    "title": "Өөрийн хүсэлтээр лавлагаа шатлалын эмнэлэгт үзүүлбэл 20 000 төгрөг төлөх нь",
    "publish_date": "Thu, 25 Jun 2026 00:00:00 GMT",
    "source": "今日报",
    "url": "https://www.unuudur.mn/a/282628",
    "category": "新闻媒体"
  },
  {
    "title": "“Тэнүүн-Огоо”-гийн А.Ганхуягийг суллах хурлыг прокурорт мэдэгдээгүй гэв",
    "publish_date": "Thu, 25 Jun 2026 00:00:00 GMT",
    "source": "今日报",
    "url": "https://www.unuudur.mn/a/282627",
    "category": "新闻媒体"
  },
  {
    "title": "Туул голд автомашинтай иргэд усанд боогджээ",
    "publish_date": "Thu, 25 Jun 2026 00:00:00 GMT",
    "source": "今日报",
    "url": "https://www.unuudur.mn/a/282641",
    "category": "新闻媒体"
  },
  {
    "title": "Дэлхийн оюуны өмчийн байгууллагын хөтөлбөрийг Монголд хэрэгжүүлнэ",
    "publish_date": "Thu, 25 Jun 2026 00:00:00 GMT",
    "source": "今日报",
    "url": "https://www.unuudur.mn/a/282625",
    "category": "新闻媒体"
  },
  {
    "title": "Хүүхдэд эрсдэлтэй 7844 объектыг шалгаж, 17 977 зөрчил илрүүлжээ",
    "publish_date": "Thu, 25 Jun 2026 00:00:00 GMT",
    "source": "今日报",
    "url": "https://www.unuudur.mn/a/282626",
    "category": "新闻媒体"
  },
  {
    "title": "“Цахим хөдөлмөр эрхлэгчид нэмэгдэж буй ч нийгмийн хамгааллын гадна үлдэх эрсдэлтэй”",
    "publish_date": "Thu, 25 Jun 2026 00:00:00 GMT",
    "source": "今日报",
    "url": "https://www.unuudur.mn/a/282624",
    "category": "新闻媒体"
  },
  {
    "title": "Ерөнхий сайд инновац, ногоон хөгжил, эрчим хүчний салбарт хамтран ажиллах сонирхлоо илэрхийлэв",
    "publish_date": "Thu, 25 Jun 2026 00:00:00 GMT",
    "source": "今日报",
    "url": "https://www.unuudur.mn/a/282640",
    "category": "新闻媒体"
  },
  {
    "title": "Зардлаа нэмж, өрөө өсгөсөөр дефолт зарлах вий",
    "publish_date": "Thu, 25 Jun 2026 00:00:00 GMT",
    "source": "今日报",
    "url": "https://www.unuudur.mn/a/282623",
    "category": "新闻媒体"
  },
  {
    "title": "Гадаадын мэргэжлийн багт уралддаг Монголын тамирчид",
    "publish_date": "Thu, 25 Jun 2026 00:00:00 GMT",
    "source": "今日报",
    "url": "https://www.unuudur.mn/a/282639",
    "category": "新闻媒体"
  },
  {
    "title": "Улсын комиссынхны гарыг хүндрүүлж, халаасыг нь түнтийлгэхгүй бол барилгыг ашиглалтад хүлээн авахгүй",
    "publish_date": "Thu, 25 Jun 2026 00:00:00 GMT",
    "source": "今日报",
    "url": "https://www.unuudur.mn/a/282637",
    "category": "新闻媒体"
  },
  {
    "title": "Монгол “Азийн хамгийн тайван улс”-ын тоонд багтлаа",
    "publish_date": "Thu, 25 Jun 2026 00:00:00 GMT",
    "source": "今日报",
    "url": "https://www.unuudur.mn/a/282622",
    "category": "新闻媒体"
  },
  {
    "title": "Хоршоо хэмээх “хорлон сүйтгэх ажиллагаа”",
    "publish_date": "Thu, 25 Jun 2026 00:00:00 GMT",
    "source": "今日报",
    "url": "https://www.unuudur.mn/a/282621",
    "category": "新闻媒体"
  },
  {
    "title": "Бодлогын хүүг 12 хувьд хэвээр үлдээжээ",
    "publish_date": "Thu, 25 Jun 2026 00:00:00 GMT",
    "source": "今日报",
    "url": "https://www.unuudur.mn/a/282620",
    "category": "新闻媒体"
  }
]