[
  {
    "title": "Ө.Шижир: Цахилгаан, дулааны үнэ нэмэхэд \"А\" гэж дуугараагүй гишүүд тамхины татвар нэмэхийг эсэргүүцэж байна",
    "publish_date": "Thu, 25 Jun 2026 18:54:00 +0800",
    "source": "IKON",
    "url": "https://ikon.mn/n/3ojb"
  },
  {
    "title": "Дубайн нэгэн үнэт эдлэлийн дэлгүүрийн эзэн алмаазан шигтгээтэй ДАШТ-ий цомыг легогоор бүтээжээ",
    "publish_date": "Thu, 25 Jun 2026 17:31:00 +0800",
    "source": "IKON",
    "url": "https://ikon.mn/n/3oj9"
  },
  {
    "title": "М.Нарантуяа-Нара: Эмэгтэйчүүд эрүүл мэндээ бодоод электрон тамхи татъя гэтэл таслан зогсоочхож байгаа юм биш байгаа",
    "publish_date": "Thu, 25 Jun 2026 17:13:00 +0800",
    "source": "IKON",
    "url": "https://ikon.mn/n/3oj8"
  },
  {
    "title": "Нийслэлийн авто замын түгжрэлийг бууруулах төслийг БНСУ-ын талын 2.7 тэрбум воны буцалтгүй тусламжаар хэрэгжүүлнэ",
    "publish_date": "Thu, 25 Jun 2026 16:53:00 +0800",
    "source": "IKON",
    "url": "https://ikon.mn/n/3oj6"
  },
  {
    "title": "Төв цэнгэлдэх хүрээлэн 2026 онд зохион байгуулах арга хэмжээний сонгон шалгаруулалт зарлалаа",
    "publish_date": "Thu, 25 Jun 2026 16:35:00 +0800",
    "source": "IKON",
    "url": "https://ikon.mn/n/3ohr"
  },
  {
    "title": "Капитрон банк: ТЕНДЕРИЙН УРИЛГА",
    "publish_date": "Thu, 25 Jun 2026 16:31:00 +0800",
    "source": "IKON",
    "url": "https://ikon.mn/n/3oj5"
  },
  {
    "title": "Моносын “Уламжлалт болон ургамлын гаралтай эмийн үйлдвэр” нээлтээ хийлээ",
    "publish_date": "Thu, 25 Jun 2026 15:41:00 +0800",
    "source": "IKON",
    "url": "https://ikon.mn/n/3oj3"
  },
  {
    "title": "О.Номинчимэг гишүүний өргөн барьсан электрон тамхинаас татвар авах агуулгатай хуулийн төслийг хэлэлцэж байна",
    "publish_date": "Thu, 25 Jun 2026 15:33:00 +0800",
    "source": "IKON",
    "url": "https://ikon.mn/n/3oiy"
  },
  {
    "title": "З.Мэндсайхан: Хамрын тамхинаас авдаг байсан 20 хувийн гаалийн татварыг онцгой албан татвараар тооцно",
    "publish_date": "Thu, 25 Jun 2026 15:25:00 +0800",
    "source": "IKON",
    "url": "https://ikon.mn/n/3oj2"
  },
  {
    "title": "Голомт банкны SocialPay аппликэйшнээр Төрийн банкны “И-Билл үйлчилгээ”-г ашиглах боломжтой боллоо",
    "publish_date": "Thu, 25 Jun 2026 15:13:00 +0800",
    "source": "IKON",
    "url": "https://ikon.mn/n/3oj1"
  },
  {
    "title": "Боксчин Т.Энхтөр допингийн зөрчил гаргаснаар эрхээ хоёр жилээр хасууллаа",
    "publish_date": "Thu, 25 Jun 2026 15:05:00 +0800",
    "source": "IKON",
    "url": "https://ikon.mn/n/3oj0"
  },
  {
    "title": "Э.Тамир: Бүх хүний тэтгэвэрт гарах насыг нэмэгдүүлсэн хуулийн төслийг хэлэлцэх гэж байна",
    "publish_date": "Thu, 25 Jun 2026 15:02:00 +0800",
    "source": "IKON",
    "url": "https://ikon.mn/n/3oiw"
  },
  {
    "title": "Төмөр замын дагуух хориг хашааг зэрлэг амьтдад ээлтэй байдлаар шинэчилнэ",
    "publish_date": "Thu, 25 Jun 2026 14:58:00 +0800",
    "source": "IKON",
    "url": "https://ikon.mn/n/3oiz"
  },
  {
    "title": "СОНС: Playtime 2026-д оролцох амьд хөгжмийн БҮХ ХАМТЛАГ, УРАН БҮТЭЭЛЧИД",
    "publish_date": "Thu, 25 Jun 2026 14:43:00 +0800",
    "source": "IKON",
    "url": "https://ikon.mn/lr/3ofl"
  },
  {
    "title": "АН-ын бүлэг Орон сууцны санхүүжилтийн төрөлжсөн банкны тухай хуулийн төсөл дээр ажлын гурав хоногийн завсарлага авлаа",
    "publish_date": "Thu, 25 Jun 2026 14:38:00 +0800",
    "source": "IKON",
    "url": "https://ikon.mn/n/3oid"
  },
  {
    "title": "\"Францын талтай хамтран Улаанбаатар дахь нислэгийн хөдөлгөөний удирдлагын төвийн тоног төхөөрөмжийг шинэчилж, Сайншандад нөөц төв байгуулна\"",
    "publish_date": "Thu, 25 Jun 2026 14:26:00 +0800",
    "source": "IKON",
    "url": "https://ikon.mn/n/3oiu"
  },
  {
    "title": "Ш.Энхийн-Од сонгогдсонгүй. Гэхдээ...",
    "publish_date": "Thu, 25 Jun 2026 13:36:00 +0800",
    "source": "IKON",
    "url": "https://ikon.mn/n/3oiv"
  },
  {
    "title": "Ж.Мөнгөншагай: Хүнд, хортой нөхцөлд ажилладаг хүмүүсийг тэтгэвэрт гаргалгүй ажлын байран дээр нь алах зорилготой хуулийг эсэргүүцэж байна",
    "publish_date": "Thu, 25 Jun 2026 13:26:00 +0800",
    "source": "IKON",
    "url": "https://ikon.mn/n/3oiq"
  },
  {
    "title": "С.Цэнгүүн: Төрийн өмчит компаниудын удирдлагуудын цалин маш өндөр байна",
    "publish_date": "Thu, 25 Jun 2026 13:00:00 +0800",
    "source": "IKON",
    "url": "https://ikon.mn/n/3oit"
  },
  {
    "title": "Өөрийн бэлдсэн хэмжээндээ ЭШ-аа өгөх орчныг бүрдүүлж байгаа учир ойр орчимд нь өндөр хаазлах, сигнал дуугаргахгүй байхыг зөвлөв",
    "publish_date": "Thu, 25 Jun 2026 12:58:00 +0800",
    "source": "IKON",
    "url": "https://ikon.mn/n/3oip"
  },
  {
    "title": "\"Хүүхдийн ордон 2\" нь шинжлэх ухаан, технологи, инновацын төв болно",
    "publish_date": "Thu, 25 Jun 2026 12:57:00 +0800",
    "source": "IKON",
    "url": "https://ikon.mn/n/3oir"
  },
  {
    "title": "ХХБ БНФУ-ын Bpifrance банктай 19.55 сая еврогийн санхүүжилтийн гэрээ байгууллаа",
    "publish_date": "Thu, 25 Jun 2026 12:56:00 +0800",
    "source": "IKON",
    "url": "https://ikon.mn/n/3ois"
  },
  {
    "title": "ФОТО: Элсэлтийн шалгалтын анхны оноо буюу 100 онооноос хэдэн оноо авсныг харуулж буй явц",
    "publish_date": "Thu, 25 Jun 2026 12:21:00 +0800",
    "source": "IKON",
    "url": "https://ikon.mn/n/3oin"
  },
  {
    "title": "БҮТ: Шалгалтын төв болгон дээр эмч, сэтгэлзүйчид ажиллаж байна",
    "publish_date": "Thu, 25 Jun 2026 11:56:00 +0800",
    "source": "IKON",
    "url": "https://ikon.mn/n/3oik"
  },
  {
    "title": "Н.Алтанхуяг: Зэсийн үнэ өсөж байгаа цаг үед АМНАТ-ийг гурав дахин бууруулна гэлээ. Г.Дамдинням хэний эрх ашигт үйлчилж байна вэ",
    "publish_date": "Thu, 25 Jun 2026 11:48:00 +0800",
    "source": "IKON",
    "url": "https://ikon.mn/n/3oim"
  },
  {
    "title": "“Петрочайна Дачин Тамсаг”, “Доншен газрын тос” компаниудад тавьсан татвар, нийгмийн даатгал, аудитын актын төлбөрийг \"хаах\" хуулийг хэлэлцэж байна",
    "publish_date": "Thu, 25 Jun 2026 11:44:00 +0800",
    "source": "IKON",
    "url": "https://ikon.mn/n/3oil"
  },
  {
    "title": "Мексик, Швейцар, Бразил хэсгээ тэргүүллээ",
    "publish_date": "Thu, 25 Jun 2026 11:35:00 +0800",
    "source": "IKON",
    "url": "https://ikon.mn/n/3oij"
  },
  {
    "title": "Олон улсын түншлэлээс дэлхийн үнэлгээ рүү: Интермед IUHW эмнэлэг олон улсын чанарын баталгаажуулалт авлаа",
    "publish_date": "Thu, 25 Jun 2026 11:09:00 +0800",
    "source": "IKON",
    "url": "https://ikon.mn/n/3oii"
  },
  {
    "title": "12 жил нөхрийнхөө хараа хяналт дор хоригдож байсан франц эмэгтэйг Пакистаны эрх баригчид чөлөөлжээ",
    "publish_date": "Thu, 25 Jun 2026 10:46:00 +0800",
    "source": "IKON",
    "url": "https://ikon.mn/n/3oia"
  },
  {
    "title": "\"Хүрээ цам-Даншиг наадам 2026\"-ын үеэр хоол үйлдвэрлэл, үйлчилгээний 170 гаруй цэг ажиллана",
    "publish_date": "Thu, 25 Jun 2026 10:45:00 +0800",
    "source": "IKON",
    "url": "https://ikon.mn/n/3oih"
  },
  {
    "title": "Төрийн бус өмчийн ерөнхий боловсролын сургуулийн сургалтын төлбөрийн талаар авах арга хэмжээний тухай",
    "publish_date": "Wed, 24 Jun 2026 00:00:00 GMT",
    "source": "蒙古国教育部",
    "url": "https://moe.gov.mn/post/176645"
  },
  {
    "title": "Боловсролын сайд Л.Энх-Амгалан МУБИС-ийн бүх салбар сургуулиуд дээр ажиллаж дууслаа",
    "publish_date": "Tue, 23 Jun 2026 00:00:00 GMT",
    "source": "蒙古国教育部",
    "url": "https://moe.gov.mn/post/176591"
  },
  {
    "title": "Салбартаа олон жил үр бүтээлтэй ажиллаж онцгой амжилт гарган, эх орныхоо хөгжил дэвшилд үнэтэй хувь нэмэр оруулсан нэр бүхий хүмүүсийг төрийн одон, медалиар шагналаа",
    "publish_date": "Mon, 22 Jun 2026 00:00:00 GMT",
    "source": "蒙古国教育部",
    "url": "https://moe.gov.mn/post/176624"
  },
  {
    "title": "ШИНЭ ЗУУНЫ МЭРГЭЖЛИЙН УР ЧАДВАРУУД ШААРДАГДАЖ БАЙНА",
    "publish_date": "Sat, 20 Jun 2026 00:00:00 GMT",
    "source": "蒙古国教育部",
    "url": "https://moe.gov.mn/post/176623"
  },
  {
    "title": "АЗИЙН ХӨГЖЛИЙН БАНКТАЙ ХАМТРАН КОЛЛЕЖУУДЫГ УР ЧАДВАРЫН ТӨВ БОЛГОН ХӨГЖҮҮЛЭХИЙГ ЗОРЬЖ БАЙНА",
    "publish_date": "Sat, 20 Jun 2026 00:00:00 GMT",
    "source": "蒙古国教育部",
    "url": "https://moe.gov.mn/post/176606"
  },
  {
    "title": "Өргөдөл гомдол",
    "publish_date": "Thu, 25 Jun 2026 00:00:00 GMT",
    "source": "蒙古国教育部",
    "url": "https://moe.gov.mn/urgudul"
  },
  {
    "title": "Түгээмэл асуулт, хариулт",
    "publish_date": "Thu, 25 Jun 2026 00:00:00 GMT",
    "source": "蒙古国教育部",
    "url": "https://moe.gov.mn/faq"
  },
  {
    "title": "Цахим үйлчилгээ",
    "publish_date": "Thu, 25 Jun 2026 00:00:00 GMT",
    "source": "蒙古国教育部",
    "url": "https://e-mongolia.mn/services/citizen/sector/5d88db8c0384dfe86ce14e67"
  },
  {
    "title": "ТУСГАЙ ЗӨВШӨӨРӨЛ",
    "publish_date": "Thu, 25 Jun 2026 00:00:00 GMT",
    "source": "蒙古国教育部",
    "url": "https://license.edu.mn/#/"
  },
  {
    "title": "Гадаадад суралцах",
    "publish_date": "Thu, 25 Jun 2026 00:00:00 GMT",
    "source": "蒙古国教育部",
    "url": "https://moe.gov.mn/study-abroad?category_id=11426"
  },
  {
    "title": "Шилэн данс",
    "publish_date": "Thu, 25 Jun 2026 00:00:00 GMT",
    "source": "蒙古国教育部",
    "url": "https://shilendans.gov.mn/organization/4308"
  },
  {
    "title": "Статистик мэдээлэл",
    "publish_date": "Thu, 25 Jun 2026 00:00:00 GMT",
    "source": "蒙古国教育部",
    "url": "https://moe.gov.mn/statistics-industry?category_id=11397"
  },
  {
    "title": "Нээлттэй хэлэлцүүлэг",
    "publish_date": "Thu, 25 Jun 2026 00:00:00 GMT",
    "source": "蒙古国教育部",
    "url": "https://moe.gov.mn/posts?category_id=11399"
  },
  {
    "title": "Хууль, эрх зүй",
    "publish_date": "Thu, 25 Jun 2026 00:00:00 GMT",
    "source": "蒙古国教育部",
    "url": "https://legalinfo.mn/mn/detail?lawId=16759958962301"
  },
  {
    "title": "Төрийн ордонтой танилцах",
    "publish_date": "Thu, 25 Jun 2026 00:00:00 GMT",
    "source": "蒙古国大呼拉尔",
    "url": "https://www.parliament.mn/nn/74270/"
  },
  {
    "title": "Үндсэн хууль /аудио/",
    "publish_date": "Thu, 25 Jun 2026 00:00:00 GMT",
    "source": "蒙古国大呼拉尔",
    "url": "https://www.parliament.mn/nn/73816/"
  },
  {
    "title": "Үндсэн хууль /дохионы хэл/",
    "publish_date": "Thu, 25 Jun 2026 00:00:00 GMT",
    "source": "蒙古国大呼拉尔",
    "url": "https://www.parliament.mn/nn/73892/"
  },
  {
    "title": "Эмнэлгийн тусламж, үйлчилгээний тухай, Төрийн нууцын тухай хуулийн төслүүдийг хэлэлцэхийг дэмжлээ",
    "publish_date": "Thu, 25 Jun 2026 00:00:00 GMT",
    "source": "蒙古国大呼拉尔",
    "url": "https://www.parliament.mn/nn/77691/"
  },
  {
    "title": "“Алтай дамнасан тогтвортой байдлын яриа хэлэлцээ-2026” олон улсын чуулганыг дөрөв дэх удаагаа зохион байгуулна",
    "publish_date": "Thu, 25 Jun 2026 00:00:00 GMT",
    "source": "蒙古国大呼拉尔",
    "url": "https://www.parliament.mn/nn/77693/"
  },
  {
    "title": "УИХ-ын дарга С.Бямбацогт Эрчим хүчний салбарын инженер, мэргэжилтнүүдтэй уулзлаа",
    "publish_date": "Thu, 25 Jun 2026 00:00:00 GMT",
    "source": "蒙古国大呼拉尔",
    "url": "https://www.parliament.mn/nn/77692/"
  },
  {
    "title": "БШУДХ: Шинжлэх ухаан, технологийн салбарт тулгамдсан асуудал, бодлогын шийдлийн талаарх мэдээллийг сонсож, Байнгын хорооны тогтоолын төслийг танилцууллаа",
    "publish_date": "Thu, 25 Jun 2026 00:00:00 GMT",
    "source": "蒙古国大呼拉尔",
    "url": "https://www.parliament.mn/nn/77690/"
  },
  {
    "title": "ЭЗБХ: Төрийн болон орон нутгийн өмчит компанийн бүтээмж, ил тод байдал, засаглалыг сайжруулах тухай хуулийн төслийн эцсийн хэлэлцүүлгийг хийв",
    "publish_date": "Thu, 25 Jun 2026 00:00:00 GMT",
    "source": "蒙古国大呼拉尔",
    "url": "https://www.parliament.mn/nn/77684/"
  },
  {
    "title": "ХЗБХ: Төсвийн төслийг улсын хөгжлийн жилийн төлөвлөгөөнд нийцүүлж, үнэн зөв, бодитой төлөвлөж, тайлагнаж хэвших шаардлагатайг анхааруулав",
    "publish_date": "Thu, 25 Jun 2026 00:00:00 GMT",
    "source": "蒙古国大呼拉尔",
    "url": "https://www.parliament.mn/nn/77683/"
  },
  {
    "title": "ТББХ: Нэр дэвшигч Ж.Сүхбаатар, Г.Эрдэнэбат нарыг Үндсэн хуулийн цэцийн гишүүнээр томилохыг дэмжлээ",
    "publish_date": "Thu, 25 Jun 2026 00:00:00 GMT",
    "source": "蒙古国大呼拉尔",
    "url": "https://www.parliament.mn/nn/77682/"
  },
  {
    "title": "ТБХ:Онцгой албан татварын тухай хуульд нэмэлт, өөрчлөлт оруулах тухай хуулийн төслийг хэлэлцэхийг дэмжиж, Улсын Их Хурлын тогтоолын төслийн хоёр дахь хэлэлцүүлгийг хийлээ",
    "publish_date": "Thu, 25 Jun 2026 00:00:00 GMT",
    "source": "蒙古国大呼拉尔",
    "url": "https://www.parliament.mn/nn/77681/"
  },
  {
    "title": "“Малчны тухай хуулийн хэрэгжилтийг дүгнэх, хууль тогтоомжийг хэрэгжүүлэх чиг үүрэг бүхий байгууллага, түүний удирдах албан тушаалтны үйл ажиллагаанд хяналт тавих, үнэлэх’’ сэдэвт сонсгол өндөрлөв",
    "publish_date": "Thu, 25 Jun 2026 00:00:00 GMT",
    "source": "蒙古国大呼拉尔",
    "url": "https://www.parliament.mn/nn/77677/"
  },
  {
    "title": "Улсын Их Хурлын гишүүн Л.Мөнхбаясгаланг Азийн парламентуудын усны асуудал хариуцсан Зөвлөлдөх зөвлөлд урилаа",
    "publish_date": "Thu, 25 Jun 2026 00:00:00 GMT",
    "source": "蒙古国大呼拉尔",
    "url": "https://www.parliament.mn/nn/77680/"
  },
  {
    "title": "УИХ-ын дарга С.Бямбацогт Австралийн Холбооны Улсаас Монгол Улсад суугаа Элчин сайд Лео Зенгийг хүлээн авч уулзав",
    "publish_date": "Thu, 25 Jun 2026 00:00:00 GMT",
    "source": "蒙古国大呼拉尔",
    "url": "https://www.parliament.mn/nn/77679/"
  },
  {
    "title": "БОХХААБХ: Монгол Улсын 2025 оны нэгдсэн төсвийн гүйцэтгэл, Засгийн газрын 2025 оны санхүүгийн нэгтгэсэн тайлангийн хоёр дахь хэлэлцүүлгийг хийлээ",
    "publish_date": "Thu, 25 Jun 2026 00:00:00 GMT",
    "source": "蒙古国大呼拉尔",
    "url": "https://www.parliament.mn/nn/77676/"
  },
  {
    "title": "Дэлхийг өөрчилсөн түүхэн 10 “анхны тохиолдол”",
    "publish_date": "Thu, 25 Jun 2026 18:50:39 +0800",
    "source": "CAAK",
    "url": "https://www.caak.mn/post/view/44080"
  },
  {
    "title": "Харь гарагийнхантай уулзсан гэж ярьдаг хүмүүсийн түүхүүд",
    "publish_date": "Thu, 25 Jun 2026 09:00:00 +0800",
    "source": "CAAK",
    "url": "https://www.caak.mn/post/view/44028"
  },
  {
    "title": "Дуудлага худалдаанд өндөр үнэд хүрсэн гэрэл зургууд",
    "publish_date": "Thu, 25 Jun 2026 07:00:07 +0800",
    "source": "CAAK",
    "url": "https://www.caak.mn/story/44072"
  },
  {
    "title": "Камерын ард нуугдсан 8 хачирхалтай итгэл үнэмшил",
    "publish_date": "Wed, 24 Jun 2026 21:30:00 +0800",
    "source": "CAAK",
    "url": "https://www.caak.mn/post/view/44070"
  },
  {
    "title": "Хүн төрөлхтний түүхэн дэх хамгийн аюултай, хамгийн хачирхалтай 4 хүнсний туршилт",
    "publish_date": "Wed, 24 Jun 2026 19:00:00 +0800",
    "source": "CAAK",
    "url": "https://www.caak.mn/post/view/44078"
  },
  {
    "title": "Казиногийн түүхэн дэх хамгийн дуулиантай 7 ялагдал",
    "publish_date": "Wed, 24 Jun 2026 13:00:14 +0800",
    "source": "CAAK",
    "url": "https://www.caak.mn/post/view/44077"
  },
  {
    "title": "Нуруу өвдөхөөс сэргийлэх Япончуудын арга",
    "publish_date": "Wed, 24 Jun 2026 11:00:00 +0800",
    "source": "CAAK",
    "url": "https://www.caak.mn/post/view/44068"
  },
  {
    "title": "Гайхалтай урт хөлөөрөө алдартай 15 бүсгүй",
    "publish_date": "Wed, 24 Jun 2026 09:00:00 +0800",
    "source": "CAAK",
    "url": "https://www.caak.mn/post/view/44075"
  },
  {
    "title": "Нордик гоо үзэсгэлэнгийн халуухан илэрхийлэл",
    "publish_date": "Wed, 24 Jun 2026 07:00:51 +0800",
    "source": "CAAK",
    "url": "https://www.caak.mn/story/44076"
  },
  {
    "title": "Спортын түүхийг өөрчилсөн 14 агшин",
    "publish_date": "Tue, 23 Jun 2026 21:00:47 +0800",
    "source": "CAAK",
    "url": "https://www.caak.mn/post/view/44071"
  },
  {
    "title": "Их хотын оршин суугчдад хамгийн түгээмэл тохиолддог сэтгэцийн 5 эмгэг",
    "publish_date": "Tue, 23 Jun 2026 15:14:00 +0800",
    "source": "CAAK",
    "url": "https://www.caak.mn/post/view/44067"
  },
  {
    "title": "Юнивишн дээрээсээ эротик кино хөнгөлөлттэй үнээр үзэх үү?",
    "publish_date": "Tue, 23 Jun 2026 15:04:50 +0800",
    "source": "CAAK",
    "url": "https://www.caak.mn/post/view/44069"
  },
  {
    "title": "Америкчууд өөрсдөө ч анзаардаггүй Америкийн соёлын хачирхалтай зүйлс",
    "publish_date": "Tue, 23 Jun 2026 11:25:00 +0800",
    "source": "CAAK",
    "url": "https://www.caak.mn/post/view/44064"
  },
  {
    "title": "Нарны аймгийн гаргууд дээрх гайхамшигт үүрийн туяа",
    "publish_date": "Tue, 23 Jun 2026 11:00:00 +0800",
    "source": "CAAK",
    "url": "https://www.caak.mn/post/view/44066"
  },
  {
    "title": "Соно, могойгоор дэлхийг гайхшруулсан үнэт эдлэлийн суутан",
    "publish_date": "Tue, 23 Jun 2026 09:00:51 +0800",
    "source": "CAAK",
    "url": "https://www.caak.mn/post/view/44065"
  },
  {
    "title": "Хоёр дахин харахаас өөр аргагүй 25 гэрэл зураг",
    "publish_date": "Tue, 23 Jun 2026 07:00:05 +0800",
    "source": "CAAK",
    "url": "https://www.caak.mn/story/44063"
  },
  {
    "title": "9 настайдаа сүйт бүсгүй болж, 10 настайдаа салсан нь: Нүжүд Алигийн дэлхийг цочроосон түүх",
    "publish_date": "Mon, 22 Jun 2026 19:01:00 +0800",
    "source": "CAAK",
    "url": "https://www.caak.mn/post/view/44058"
  },
  {
    "title": "Гэдэс томроод байна уу? Тэгвэл бурууг зөвхөн хоолноос хайх хэрэггүй!",
    "publish_date": "Mon, 22 Jun 2026 18:18:32 +0800",
    "source": "CAAK",
    "url": "https://www.caak.mn/post/view/44050"
  },
  {
    "title": "Нөмрөгтэй махлаг грек эр яагаад 1970-аад оны секс бэлгэ тэмдэг болсон бэ?",
    "publish_date": "Mon, 22 Jun 2026 15:18:00 +0800",
    "source": "CAAK",
    "url": "https://www.caak.mn/post/view/44057"
  },
  {
    "title": "Дэлхийн хамгийн нарийхан хот болох Яньцзинд хүмүүс хэрхэн амьдардаг вэ?",
    "publish_date": "Mon, 22 Jun 2026 15:00:00 +0800",
    "source": "CAAK",
    "url": "https://www.caak.mn/post/view/44059"
  },
  {
    "title": "Хүйтэн шүршүүрээр чийрэгжих нь зөв үү?",
    "publish_date": "Mon, 22 Jun 2026 11:47:00 +0800",
    "source": "CAAK",
    "url": "https://www.caak.mn/post/view/44048"
  },
  {
    "title": "Дэлхийн хамгийн хурдан галт тэрэг хэрхэн бий болсон бэ?",
    "publish_date": "Mon, 22 Jun 2026 10:21:45 +0800",
    "source": "CAAK",
    "url": "https://www.caak.mn/post/view/44038"
  },
  {
    "title": "Анжелина Жолигийн залуу нас",
    "publish_date": "Mon, 22 Jun 2026 07:04:00 +0800",
    "source": "CAAK",
    "url": "https://www.caak.mn/story/44054"
  },
  {
    "title": "Их хямралын үеэр бий болсон сонирхолтой зүйлс",
    "publish_date": "Sun, 21 Jun 2026 21:00:27 +0800",
    "source": "CAAK",
    "url": "https://www.caak.mn/post/view/44056"
  },
  {
    "title": "Өмнөд Солонгосын өдөр тутмын амьдралын сонирхолтой шийдлүүд",
    "publish_date": "Sun, 21 Jun 2026 15:00:00 +0800",
    "source": "CAAK",
    "url": "https://www.caak.mn/post/view/44055"
  },
  {
    "title": "Олимпийн тамирчдын хоолны дэглэм: Өдөрт 1500-3500 калори иддэг тамирчид юу хэрэглэдэг вэ?",
    "publish_date": "Sun, 21 Jun 2026 13:00:00 +0800",
    "source": "CAAK",
    "url": "https://www.caak.mn/post/view/44036"
  },
  {
    "title": "Нийгмийн дүрмийг эвдсэн 10 зоригт эмэгтэй",
    "publish_date": "Sun, 21 Jun 2026 11:08:00 +0800",
    "source": "CAAK",
    "url": "https://www.caak.mn/post/view/44052"
  },
  {
    "title": "Лондонгийн хамгийн эртний сэтгэцийн эмнэлгийн хар түүх",
    "publish_date": "Sun, 21 Jun 2026 09:00:11 +0800",
    "source": "CAAK",
    "url": "https://www.caak.mn/post/view/44051"
  },
  {
    "title": "Нууцлаг гэрэл зурагчин Алекс Силийн халуухан бүтээлүүд",
    "publish_date": "Sun, 21 Jun 2026 07:00:00 +0800",
    "source": "CAAK",
    "url": "https://www.caak.mn/story/44045"
  },
  {
    "title": "Эцгийнхээ биелээгүй мөрөөдлийн золиос болсон охины түүх 😢",
    "publish_date": "Sat, 20 Jun 2026 22:05:00 +0800",
    "source": "CAAK",
    "url": "https://www.caak.mn/post/view/44039"
  },
  {
    "title": "Таны төсөөллийг эвдэх 26 сонирхолтой баримт",
    "publish_date": "Sat, 20 Jun 2026 19:30:00 +0800",
    "source": "CAAK",
    "url": "https://www.caak.mn/post/view/44060"
  },
  {
    "title": "Бодит баримтаар батлагдсан 5 аймшигт түүх",
    "publish_date": "Sat, 20 Jun 2026 19:01:00 +0800",
    "source": "CAAK",
    "url": "https://www.caak.mn/post/view/44037"
  },
  {
    "title": "Тэрбумтнуудын уудаг эмээс ч илүү үр дүнтэй, үнэ төлбөргүй 7 зуршил",
    "publish_date": "Sat, 20 Jun 2026 18:50:00 +0800",
    "source": "CAAK",
    "url": "https://www.caak.mn/post/view/44053"
  },
  {
    "title": "Европын хамгийн үзэсгэлэнтэй 8 тосгон",
    "publish_date": "Sat, 20 Jun 2026 17:10:00 +0800",
    "source": "CAAK",
    "url": "https://www.caak.mn/post/view/44043"
  },
  {
    "title": "Таныг гайхшруулах 15 сонирхолтой баримт",
    "publish_date": "Sat, 20 Jun 2026 15:10:00 +0800",
    "source": "CAAK",
    "url": "https://www.caak.mn/post/view/44047"
  },
  {
    "title": "Яагаад бид стрессдэхээрээ өвчилдөг вэ? Стресс дархлаанд яаж нөлөөлдөг вэ?",
    "publish_date": "Sat, 20 Jun 2026 11:00:00 +0800",
    "source": "CAAK",
    "url": "https://www.caak.mn/post/view/44049"
  },
  {
    "title": "Дэлхийн ховор амьтдыг байгальд нь харах боломжтой шилдэг 10 газар",
    "publish_date": "Sat, 20 Jun 2026 09:10:00 +0800",
    "source": "CAAK",
    "url": "https://www.caak.mn/post/view/44029"
  },
  {
    "title": "Амтат рамэн бэлдэх хялбар жор",
    "publish_date": "Sat, 20 Jun 2026 07:18:00 +0800",
    "source": "CAAK",
    "url": "https://www.caak.mn/post/view/44046"
  },
  {
    "title": "Өөрсдийгөө золиослон мянга мянган хүний амийг аварсан хүмүүс",
    "publish_date": "Fri, 19 Jun 2026 21:00:00 +0800",
    "source": "CAAK",
    "url": "https://www.caak.mn/post/view/44021"
  },
  {
    "title": "Хүмүүсийг амьтны хүрээлэнгийн үзмэр болгосон ичгүүрт түүх",
    "publish_date": "Fri, 19 Jun 2026 19:18:00 +0800",
    "source": "CAAK",
    "url": "https://www.caak.mn/post/view/44024"
  },
  {
    "title": "Дэлхий дээр үнэхээр байдаг гэхэд итгэмээргүй 10 зүйл",
    "publish_date": "Fri, 19 Jun 2026 17:18:00 +0800",
    "source": "CAAK",
    "url": "https://www.caak.mn/post/view/44022"
  },
  {
    "title": "Гэрэл зураг дээр хэрхэн туранхай гоё гарах вэ?",
    "publish_date": "Fri, 19 Jun 2026 15:01:00 +0800",
    "source": "CAAK",
    "url": "https://www.caak.mn/post/view/44044"
  },
  {
    "title": "Усан дээр хөвөх мэт хамгийн үзэсгэлэнт 10 цайз",
    "publish_date": "Fri, 19 Jun 2026 11:08:00 +0800",
    "source": "CAAK",
    "url": "https://www.caak.mn/post/view/44041"
  },
  {
    "title": "Энгийн нүдээр харах боломжгүй 5 гайхалтай дүр зураг",
    "publish_date": "Fri, 19 Jun 2026 09:05:00 +0800",
    "source": "CAAK",
    "url": "https://www.caak.mn/post/view/44042"
  },
  {
    "title": "1950-аад оны хамгийн төгс галбиртай бүсгүй",
    "publish_date": "Fri, 19 Jun 2026 07:00:00 +0800",
    "source": "CAAK",
    "url": "https://www.caak.mn/story/44031"
  },
  {
    "title": "50 жил эзгүйрсэн сүмийг &quot;сүнснүүд&quot; хэрхэн аварсан бэ?",
    "publish_date": "Thu, 18 Jun 2026 19:08:00 +0800",
    "source": "CAAK",
    "url": "https://www.caak.mn/post/view/44016"
  },
  {
    "title": "Эрч хүчийг бүтэн өдрийн турш хадгалахад туслах шилдэг 10 хөнгөн зууш",
    "publish_date": "Thu, 18 Jun 2026 17:35:00 +0800",
    "source": "CAAK",
    "url": "https://www.caak.mn/post/view/44035"
  },
  {
    "title": "Тесла үхэшгүй мөнхийн тухай ярьсан уу? Суут зохион бүтээгчийн 3 гайхалтай санаа",
    "publish_date": "Thu, 18 Jun 2026 17:00:00 +0800",
    "source": "CAAK",
    "url": "https://www.caak.mn/post/view/44019"
  },
  {
    "title": "Берингийн хоолойн цуст түүх: Чукчууд ба эскимосуудын өшөө авалт",
    "publish_date": "Thu, 18 Jun 2026 15:05:00 +0800",
    "source": "CAAK",
    "url": "https://www.caak.mn/post/view/44025"
  },
  {
    "title": "ISO 59000 ТОЙРОГ ЭДИЙН ЗАСАГ ЧУУЛГАН",
    "publish_date": "Tue, 23 Jun 2026 00:00:00 GMT",
    "source": "蒙古国标准计量局",
    "url": "https://www.masm.gov.mn/website/news.aspx?id=3676"
  },
  {
    "title": "СТАНДАРТ, ХЭМЖИЛ ЗҮЙН ГАЗРЫН 2026 ОНЫ ЭХНИЙ ХАГАС ЖИЛИЙН ГҮЙЦЭТГЭЛИЙН ТӨЛӨВЛӨГӨӨНИЙ ТАЙЛАНГ ХЭЛЭЛЦЛЭЭ",
    "publish_date": "Fri, 19 Jun 2026 00:00:00 GMT",
    "source": "蒙古国标准计量局",
    "url": "https://www.masm.gov.mn/website/news.aspx?id=3673"
  },
  {
    "title": "“СТАНДАРТ, ХӨГЖЛИЙН ТУЛГУУР – НИЙГМИЙН БАТАЛГАА” ЦАХИМ УРАЛДААНЫ ШАГНАЛЫГ ГАРДУУЛЛАА",
    "publish_date": "Fri, 05 Jun 2026 00:00:00 GMT",
    "source": "蒙古国标准计量局",
    "url": "https://www.masm.gov.mn/website/news.aspx?id=3641"
  },
  {
    "title": "ХАНГАЙН БҮСИЙН ИТГЭМЖЛЭГДСЭН ЛАБОРАТОРИЙН АЛБАН ХААГЧДЫН СУРГАЛТ БОЛЛОО",
    "publish_date": "Fri, 05 Jun 2026 00:00:00 GMT",
    "source": "蒙古国标准计量局",
    "url": "https://www.masm.gov.mn/website/news.aspx?id=3642"
  },
  {
    "title": "ҮНДЭСНИЙ ХЭМЖЭЭНД СТАНДАРТЫН ХЭРЭГЖИЛТИЙГ ХАНГАЖ АЖИЛЛАХЫГ ҮҮРЭГ БОЛГОЛОО",
    "publish_date": "Wed, 03 Jun 2026 00:00:00 GMT",
    "source": "蒙古国标准计量局",
    "url": "https://www.masm.gov.mn/website/news.aspx?id=3607"
  },
  {
    "title": "Шадар сайдын цаг нэвтрүүлгийн хэсгээс...",
    "publish_date": "Wed, 03 Jun 2026 00:00:00 GMT",
    "source": "蒙古国标准计量局",
    "url": "https://www.masm.gov.mn/website/news.aspx?id=3583"
  },
  {
    "title": "Стандартчилал, техникийн зохицуулалт, тохирлын үнэлгээний итгэмжлэлийн тухай хуулийн шинэчилсэн найруулгын төслийг боловсруулан, Засгийн газрын хуралдаанаар хэлэлцүүлж Улсын Их Хуралд өргөн мэдүүлэх бэлтгэл ажлыг ханган ажиллаж байна.",
    "publish_date": "Tue, 02 Jun 2026 00:00:00 GMT",
    "source": "蒙古国标准计量局",
    "url": "https://www.masm.gov.mn/website/news.aspx?id=3582"
  },
  {
    "title": "СТАНДАРТЧИЛАЛ, ТЕХНИКИЙН ЗОХИЦУУЛАЛТ, ТОХИРЛЫН ҮНЭЛГЭЭНИЙ ИТГЭМЖЛЭЛИЙН ТУХАЙ ХУУЛИЙН ТӨСӨЛД САНАЛ АВАХ ОЛОН НИЙТИЙН ХЭЛЭЛЦҮҮЛЭГ БОЛЛОО",
    "publish_date": "Fri, 29 May 2026 00:00:00 GMT",
    "source": "蒙古国标准计量局",
    "url": "https://www.masm.gov.mn/website/news.aspx?id=3581"
  },
  {
    "title": "СОРЬЦЫН ХЯНАЛТЫН ГАЗРЫН ЭРДЭНИЙН ЧУЛУУНЫ ЛАБОРАТОРИЙН ДҮГНЭЛТИЙГ ЦАХИМЖУУЛНА",
    "publish_date": "Thu, 28 May 2026 00:00:00 GMT",
    "source": "蒙古国标准计量局",
    "url": "https://www.masm.gov.mn/website/news.aspx?id=3580"
  },
  {
    "title": "НИЙСЛЭЛИЙН ЛАБОРАТОРИЙН ЭРХ ЗҮЙН ОРЧНЫГ БОЛОВСРОНГУЙ БОЛГОЖ, ҮЙЛ АЖИЛЛАГААГ ЭРЧИМЖҮҮЛНЭ",
    "publish_date": "Wed, 27 May 2026 00:00:00 GMT",
    "source": "蒙古国标准计量局",
    "url": "https://www.masm.gov.mn/website/news.aspx?id=3578"
  },
  {
    "title": "MNS ISO 19011:2020 МЕНЕЖМЕНТИЙН ТОГТОЛЦООНД АУДИТ ЯВУУЛАХ ЗААВАР СЭДЭВТ СУРГАЛТ ЭХЭЛЛЭЭ",
    "publish_date": "Tue, 26 May 2026 00:00:00 GMT",
    "source": "蒙古国标准计量局",
    "url": "https://www.masm.gov.mn/website/news.aspx?id=3577"
  },
  {
    "title": "Шадар сайд Н.Номтойбаяр “Стандарт бол иргэдийн аюулгүй байдал, чанарын баталгаа юм. Иймд лаборатори, Итгэмжлэлийн байгууллагуудыг зах зээлийн зарчмаар хөгжүүлнэ. Санхүүгийн бие даасан тогтолцоог бүрдүүлнэ”",
    "publish_date": "Mon, 25 May 2026 00:00:00 GMT",
    "source": "蒙古国标准计量局",
    "url": "https://www.masm.gov.mn/website/news.aspx?id=3611"
  },
  {
    "title": "МОНГОЛ УЛСЫН ЗАСГИЙН ГАЗРЫН 2026 ОНЫ 06 ДУГААР САРЫН 17-НЫ ӨДРИЙН 253 ДУГААР ТОГТООЛООР БАТЛАГДСАН “МЭРГЭЖЛИЙН НЭГДСЭН ХОЛБООГ БҮРТГЭХ ЖУРАМ”-ЫН ТАНИЛЦУУЛГЫГ ЕРӨНХИЙ САЙДЫН АЖЛЫН АЛБАНААС ХИЙХ ТУЛ МЭРГЭЖЛИЙН ХОЛБООДЫН ТӨЛӨӨЛЛИЙГ УРЬЖ БАЙНА",
    "publish_date": "Thu, 25 Jun 2026 10:15:16 +0000",
    "source": "蒙古国工业和矿产资源部",
    "url": "https://mmhi.gov.mn/2026/06/25/%d0%bc%d0%be%d0%bd%d0%b3%d0%be%d0%bb-%d1%83%d0%bb%d1%81%d1%8b%d0%bd-%d0%b7%d0%b0%d1%81%d0%b3%d0%b8%d0%b9%d0%bd-%d0%b3%d0%b0%d0%b7%d1%80%d1%8b%d0%bd-2026-%d0%be%d0%bd%d1%8b-06-%d0%b4%d1%83%d0%b3%d0%b0/"
  },
  {
    "title": "БНСУ-ЫН ХУДАЛДААНЫ САЙД Ё ХАН ГҮГ ХҮЛЭЭН АВЧ УУЛЗАВ",
    "publish_date": "Thu, 18 Jun 2026 02:15:18 +0000",
    "source": "蒙古国工业和矿产资源部",
    "url": "https://mmhi.gov.mn/2026/06/18/%d0%b1%d0%bd%d1%81%d1%83-%d1%8b%d0%bd-%d1%85%d1%83%d0%b4%d0%b0%d0%bb%d0%b4%d0%b0%d0%b0%d0%bd%d1%8b-%d1%81%d0%b0%d0%b9%d0%b4-%d1%91-%d1%85%d0%b0%d0%bd-%d0%b3%d2%af%d0%b3-%d1%85%d2%af%d0%bb%d1%8d%d1%8d/"
  },
  {
    "title": "БҮГД НАЙРАМДАХ КАЗАХСТАН УЛСТАЙ ГАЗРЫН ТОСНЫ САЛБАРТ ХАМТАРСАН АЖЛЫН ХЭСЭГ БАЙГУУЛАХААР ТОХИРЛОО",
    "publish_date": "Thu, 18 Jun 2026 01:59:25 +0000",
    "source": "蒙古国工业和矿产资源部",
    "url": "https://mmhi.gov.mn/2026/06/18/%d0%b1%d2%af%d0%b3%d0%b4-%d0%bd%d0%b0%d0%b9%d1%80%d0%b0%d0%bc%d0%b4%d0%b0%d1%85-%d0%ba%d0%b0%d0%b7%d0%b0%d1%85%d1%81%d1%82%d0%b0%d0%bd-%d1%83%d0%bb%d1%81%d1%82%d0%b0%d0%b9-%d0%b3%d0%b0%d0%b7%d1%80/"
  },
  {
    "title": "БНЭУ-ЫН ЭКСИМ БАНКНЫ ТӨЛӨӨЛӨГЧДИЙГ ХҮЛЭЭН АВЧ УУЛЗАВ",
    "publish_date": "Thu, 11 Jun 2026 07:58:13 +0000",
    "source": "蒙古国工业和矿产资源部",
    "url": "https://mmhi.gov.mn/2026/06/11/%d0%b1%d0%bd%d1%8d%d1%83-%d1%8b%d0%bd-%d1%8d%d0%ba%d1%81%d0%b8%d0%bc-%d0%b1%d0%b0%d0%bd%d0%ba%d0%bd%d1%8b-%d1%82%d3%a9%d0%bb%d3%a9%d3%a9%d0%bb%d3%a9%d0%b3%d1%87%d0%b4%d0%b8%d0%b9%d0%b3-%d1%85%d2%af/"
  },
  {
    "title": "БЕЛЬГИЙН ХААНТ УЛСААС МОНГОЛ УЛСЫГ ХАВСРАН СУУГАА ЭЛЧИН САЙД БРУНО АНЖЕЛЕТЫГ ХҮЛЭЭН АВЧ УУЛЗЛАА",
    "publish_date": "Thu, 28 May 2026 07:39:53 +0000",
    "source": "蒙古国工业和矿产资源部",
    "url": "https://mmhi.gov.mn/2026/05/28/%d0%b1%d0%b5%d0%bb%d1%8c%d0%b3%d0%b8%d0%b9%d0%bd-%d1%85%d0%b0%d0%b0%d0%bd%d1%82-%d1%83%d0%bb%d1%81%d0%b0%d0%b0%d1%81-%d0%bc%d0%be%d0%bd%d0%b3%d0%be%d0%bb-%d1%83%d0%bb%d1%81%d1%8b%d0%b3-%d1%85%d0%b0/"
  },
  {
    "title": "АЖ ҮЙЛДВЭР, ЭРДЭС БАЯЛГИЙН САЙД Г.ДАМДИННЯМ АШИГТ МАЛТМАЛЫН ТУХАЙ ХУУЛЬД НЭМЭЛТ, ӨӨРЧЛӨЛТ ОРУУЛАХ ТУХАЙ ХУУЛИЙН ТӨСӨЛ ӨРГӨН МЭДҮҮЛЭВ",
    "publish_date": "Tue, 26 May 2026 06:19:54 +0000",
    "source": "蒙古国工业和矿产资源部",
    "url": "https://mmhi.gov.mn/2026/05/26/%d0%b0%d0%b6-%d2%af%d0%b9%d0%bb%d0%b4%d0%b2%d1%8d%d1%80-%d1%8d%d1%80%d0%b4%d1%8d%d1%81-%d0%b1%d0%b0%d1%8f%d0%bb%d0%b3%d0%b8%d0%b9%d0%bd-%d1%81%d0%b0%d0%b9%d0%b4-%d0%b3-%d0%b4%d0%b0%d0%bc%d0%b4-15/"
  },
  {
    "title": "АЖ ҮЙЛДВЭР, ЭРДЭС БАЯЛГИЙН САЙДЫН ЗӨВЛӨЛИЙН ЭЭЛЖИТ ХУРАЛДААН БОЛЛОО",
    "publish_date": "Mon, 25 May 2026 07:57:09 +0000",
    "source": "蒙古国工业和矿产资源部",
    "url": "https://mmhi.gov.mn/2026/05/25/%d0%b0%d0%b6-%d2%af%d0%b9%d0%bb%d0%b4%d0%b2%d1%8d%d1%80-%d1%8d%d1%80%d0%b4%d1%8d%d1%81-%d0%b1%d0%b0%d1%8f%d0%bb%d0%b3%d0%b8%d0%b9%d0%bd-%d1%81%d0%b0%d0%b9%d0%b4%d1%8b%d0%bd-%d0%b7%d3%a9%d0%b2%d0%bb-3/"
  },
  {
    "title": "АҮЭБ-ИЙН САЙД Г.ДАМДИННЯМ БНИУ-ЫН ЭКСПОРТЫН ЗЭЭЛИЙН АГЕНТЛАГ (SACE)-ИЙН ЕРӨНХИЙЛӨГЧ ГУЛИЭЛМО ПИККИГ ХҮЛЭЭН АВЧ УУЛЗАВ",
    "publish_date": "Fri, 22 May 2026 01:24:43 +0000",
    "source": "蒙古国工业和矿产资源部",
    "url": "https://mmhi.gov.mn/2026/05/22/%d0%b0%d2%af%d1%8d%d0%b1-%d0%b8%d0%b9%d0%bd-%d1%81%d0%b0%d0%b9%d0%b4-%d0%b3-%d0%b4%d0%b0%d0%bc%d0%b4%d0%b8%d0%bd%d0%bd%d1%8f%d0%bc-%d0%b1%d0%bd%d0%b8%d1%83-%d1%8b%d0%bd-%d1%8d%d0%ba%d1%81%d0%bf%d0%be/"
  },
  {
    "title": "АҮЭБ-ИЙН САЙД Г.ДАМДИННЯМ БНСУ-ЫН УУЛ УУРХАЙН НӨХӨН СЭРГЭЭЛТ, АШИГТ МАЛТМАЛЫН КОРПОРАЦИ (КОМИР)-Н МОНГОЛ ДАХЬ СУУРИН ТӨЛӨӨЛӨГЧИЙН ГАЗРЫН ЗАХИРАЛ БАН СОН БЭКИЙГ ХҮЛЭЭН АВЧ УУЛЗАВ",
    "publish_date": "Wed, 20 May 2026 01:23:58 +0000",
    "source": "蒙古国工业和矿产资源部",
    "url": "https://mmhi.gov.mn/2026/05/20/%d0%b0%d2%af%d1%8d%d0%b1-%d0%b8%d0%b9%d0%bd-%d1%81%d0%b0%d0%b9%d0%b4-%d0%b3-%d0%b4%d0%b0%d0%bc%d0%b4%d0%b8%d0%bd%d0%bd%d1%8f%d0%bc-%d0%b1%d0%bd%d1%81%d1%83-%d1%8b%d0%bd-%d1%83%d1%83%d0%bb-%d1%83%d1%83/"
  },
  {
    "title": "ГАЗРЫН ТОС БОЛОВСРУУЛАХ ҮЙЛДВЭРИЙН БҮТЭЭН БАЙГУУЛАЛТЫН АЖЛЫГ ШУУРХАЙЛАХАД ЗАСГИЙН ГАЗАР ДЭМЖЛЭГ ҮЗҮҮЛНЭ",
    "publish_date": "Fri, 15 May 2026 02:01:53 +0000",
    "source": "蒙古国工业和矿产资源部",
    "url": "https://mmhi.gov.mn/2026/05/15/%d0%b3%d0%b0%d0%b7%d1%80%d1%8b%d0%bd-%d1%82%d0%be%d1%81-%d0%b1%d0%be%d0%bb%d0%be%d0%b2%d1%81%d1%80%d1%83%d1%83%d0%bb%d0%b0%d1%85-%d2%af%d0%b9%d0%bb%d0%b4%d0%b2%d1%8d%d1%80%d0%b8%d0%b9%d0%bd-%d0%b1/"
  },
  {
    "title": "Хүмүүнлэгийн андууддаа талархал илэрхийллээ",
    "publish_date": "Thu, 25 Jun 2026 00:00:00 GMT",
    "source": "蒙古国紧急情况总局",
    "url": "https://nema.gov.mn/post/174979"
  },
  {
    "title": "Цагааннуур сум дахь эрэн хайх, аврах салбарын үйл ажиллагааг эхлүүллээ",
    "publish_date": "Thu, 25 Jun 2026 00:00:00 GMT",
    "source": "蒙古国紧急情况总局",
    "url": "https://nema.gov.mn/post/170820"
  },
  {
    "title": "Монгол Улсад төрийн цэргийн болон хууль сахиулах байгууллагын эмэгтэй алба хаагчид хурандаа цол олгож эхэлсний 30 жилийн ой өнөөдөр тохиож байна",
    "publish_date": "Thu, 25 Jun 2026 00:00:00 GMT",
    "source": "蒙古国紧急情况总局",
    "url": "https://nema.gov.mn/post/162024"
  },
  {
    "title": "\"ТӨРИЙН БОДЛОГО-ЖИЖИГ, ДУНД ҮЙЛДВЭР, ХАРЬЦУУЛСАН СУДАЛГАА\" НОМ УНШИГЧИЙН ГАР ДЭЭР ОЧЛОО",
    "publish_date": "Thu, 25 Jun 2026 00:00:00 GMT",
    "source": "中小企业局",
    "url": "https://sme.gov.mn/news/16203978159443/16203978159460/17766807135802",
    "category": "党政机关"
  },
  {
    "title": "Неймар 980 хоногийн дараа Бразилын шигшээ багийн төлөө тоглолоо",
    "publish_date": "Thu, 25 Jun 2026 00:00:00 GMT",
    "source": "蒙通社",
    "url": "https://montsame.mn/mn/read/403027",
    "category": "新闻媒体"
  },
  {
    "title": "COP17 бага хурлын хүрээнд “Сайн санаачилга, шилдэг шийдэл”-ийг хүлээн авч эхэллээ",
    "publish_date": "Thu, 25 Jun 2026 00:00:00 GMT",
    "source": "蒙通社",
    "url": "https://montsame.mn/mn/read/403123",
    "category": "新闻媒体"
  },
  {
    "title": "Ихэнх нутгаар өнөөдөр бороотой",
    "publish_date": "Thu, 25 Jun 2026 00:00:00 GMT",
    "source": "蒙通社",
    "url": "https://montsame.mn/mn/read/403026",
    "category": "新闻媒体"
  },
  {
    "title": "САЙД Ж.АЛДАРЖАВХЛАН ОЛОН УЛСЫН ОЮУТНЫ СПОРТЫН ХОЛБООНЫ ТӨЛӨӨЛӨГЧДИЙГ ХҮЛЭЭН АВЧ УУЛЗЛАА",
    "publish_date": "Thu, 25 Jun 2026 00:00:00 GMT",
    "source": "蒙古国文化体育旅游与青年部",
    "url": "https://mocsty.gov.mn/news/062503",
    "category": "党政机关"
  },
  {
    "title": "МОНГОЛ УЛСЫН ХҮҮХЭЛДЭЙН ТЕАТР “СИБИРЬ TERRA MAGICA” НААДАМД АМЖИЛТТАЙ ОРОЛЦЛОО",
    "publish_date": "Thu, 25 Jun 2026 00:00:00 GMT",
    "source": "蒙古国文化体育旅游与青年部",
    "url": "https://mocsty.gov.mn/news/062501",
    "category": "党政机关"
  },
  {
    "title": "“Автотээврийн хэрэгслийн бүртгэл хөтлөх, улсын дугаар олгох журам”-төслийн хэлэлцүүлэгт таныг урьж байна.",
    "publish_date": "Thu, 25 Jun 2026 00:00:00 GMT",
    "source": "道路与交通运输部",
    "url": "https://mrt.gov.mn/i/5112",
    "category": "党政机关"
  },
  {
    "title": "Нислэгийн хөдөлгөөний удирдлагын төвийн систем, тоног төхөөрөмжийн шинэчлэлийг санхүүжүүлэх экспортын зээлийн гэрээнүүдэд гарын үсэг зурлаа",
    "publish_date": "Thu, 25 Jun 2026 00:00:00 GMT",
    "source": "道路与交通运输部",
    "url": "https://mrt.gov.mn/i/5109",
    "category": "党政机关"
  },
  {
    "title": "Хөдлөх бүрэлдэхүүн жолоодох эрхийн үнэмлэх горилогчдын анхааралд",
    "publish_date": "Thu, 25 Jun 2026 00:00:00 GMT",
    "source": "道路与交通运输部",
    "url": "https://mrt.gov.mn/i/5108",
    "category": "党政机关"
  },
  {
    "title": "NEMA Podcast-17",
    "publish_date": "Thu, 25 Jun 2026 00:00:00 GMT",
    "source": "蒙古国紧急情况总局",
    "url": "https://nema.gov.mn/post/176687",
    "category": "党政机关"
  },
  {
    "title": "Венесуэлд 7.5 магнитудын хүчтэй газар хөдөлжээ",
    "publish_date": "Thu, 25 Jun 2026 00:00:00 GMT",
    "source": "蒙古国紧急情况总局",
    "url": "https://nema.gov.mn/post/176683",
    "category": "党政机关"
  },
  {
    "title": "Эмч,эмнэлгийн мэргэжилтнүүд мэдлэг, ур чадвараа  дээшлүүлж, харилцан туршлага солилцлоо",
    "publish_date": "Thu, 25 Jun 2026 00:00:00 GMT",
    "source": "蒙古国紧急情况总局",
    "url": "https://nema.gov.mn/post/176665",
    "category": "党政机关"
  },
  {
    "title": "ЭРЧИМ ХҮЧНИЙ САЛБАРЫН МЭДЭЭЛЭЛ ИРГЭН БҮРТ НЭЭЛТТЭЙ БОЛЛОО",
    "publish_date": "Thu, 25 Jun 2026 00:00:00 GMT",
    "source": "能源部",
    "url": "https://energy.gov.mn/post/176662",
    "category": "党政机关"
  },
  {
    "title": "СЭРГЭЭГДЭХ ЭРЧИМ ХҮЧНИЙ НӨӨЦ, ЭХ ҮҮСВЭРИЙН СУДАЛГАА ШИНЖИЛГЭЭ БОЛОН УС ЦАГ УУРЫН АЖИГЛАЛТЫН ЗОРИУЛАЛТТАЙ 15 НЭР ТӨРЛИЙН ТОНОГ ТӨХӨӨРӨМЖИЙГ ГААЛЬ, НӨАТ-ААС ЧӨЛӨӨЛӨХ ТОГТООЛЫГ БАТАЛЛАА",
    "publish_date": "Thu, 25 Jun 2026 00:00:00 GMT",
    "source": "气象与环境研究局",
    "url": "https://namem.gov.mn/d/news/846",
    "category": "党政机关"
  },
  {
    "title": "“Авлигатай тэмцэх Үндэсний хөтөлбөр”-ийн сургалт болов",
    "publish_date": "Thu, 25 Jun 2026 00:00:00 GMT",
    "source": "央行",
    "url": "https://www.mongolbank.mn/mn/r/12529",
    "category": "党政机关"
  }
]